[{"id": "terroristactivity1", "Geos": ["Uptown D.C.", "Boatmen", "U.S.", "Vastopolis", "Maryland", "Charlotte", "N.C.", "New Mexico"], "People": ["Humberto L. Richard", "Vastopolis", "Richard"]}, {"id": "terroristactivity2", "Geos": ["Joelle", "ALBANY", "N.Y.", "Smogtown", "Suburbia"], "People": ["Rooks Joelle", "Stormy Berniece"]}, {"id": "terroristactivity3", "Geos": [], "People": ["Hiroko", "Michaele Josefa", "Jacques", "Latino", "Bill", "Tommie Bretz", "My Tots Top Your Tot Bayh", "Maria ``below-the-podium", "Edelmira Tillman", "Tipper", "Bernie Rice", "Evens", "Cuomo", "pro-Hillary", "Chaparro", "Davina Quarles"]}, {"id": "terroristactivity4", "Geos": ["Colorado", "Indiana", "KALAMAZOO", "Kalamazoo", "Mich.", "Battle Creek", "Great Lakes", "Santa Barbara", "Calif.", "Vastopolis", "Yosemite", "Arkansas"], "People": ["Chelsie", "Nail", "Rudy Colin", "Dillon Crutcher", "Jessi Jacques Maris Cervantez", "Maris Cervantez", "Vastopolis", "Codi", "Jessi Jacques", "Evangeline Stagg Bui", "Cervantez", "Bobby Derryberry", "Derryberry", "Stagg", "Billy Codi", "Hiroko", "Crutcher", "Jacques", "Fred D. Rosa's", "Evangeline Stagg", "Royce Nail", "Hiroko Crossman", "Maryalice Dean", "Hillary"]}, {"id": "terroristactivity5", "Geos": ["France", "U.S.", "Germany", "Spain"], "People": ["Telefonica de Espana SA", "Harlow Matherne"]}, {"id": "terroristactivity6", "Geos": ["Solitaire", "America", "Hong Kong", "Tokyo", "Indochina", "Vietnam", "Minesweeper"], "People": ["Noel", "Cafe Tam Tam", "Tommie Noel", "Dutton Minnie", "Minnie"]}, {"id": "terroristactivity7", "Geos": [], "People": ["Vastopolis"]}, {"id": "terroristactivity8", "Geos": ["U.S."], "People": ["Wicklund Artis", "Savage", "Lutes", "Max Superlong +1.25 SB", "Wilson Jack Kramer Autograph", "Chantay", "Jina Whitt Winford", "Raise", "Poulos", "Vastopolis", "Nicolle Lutes", "Pimental", "Hubert Angelo"]}, {"id": "terroristactivity9", "Geos": [], "People": ["Insurer Generali"]}, {"id": "terroristactivity10", "Geos": ["Hong Kong", "Jacobo Vargas", "Hong Kong's", "Britain", "London", "U.K."], "People": ["Jacobo Vargas", "Jardine Fleming Affiliates Fined", "Collin Carpenter", "Roberto Thomasina", "Paulene Winkler", "Jahnke Jensen", "Watson Wyatt Worldwide", "Lenny Kane", "Maze Spillman", "Fransisca Rutha", "JFAM", "Robert Fleming", "Weaver", "Winkler", "Thomasina", "Jacobo Vargas's", "Roberto Vargas", "Markita Harrison", "Roberto Vargas's", "Jardine Fleming"]}, {"id": "terroristactivity11", "Geos": ["America", "Lakeside", "Arcadia", "Mo."], "People": ["Herma Howard", "Landowner Makes Mountain", "Howard", "Dean", "Verda Scottie", "Prior", "Jackelyn Blazer", "Davina Prior", "Completer Award", "thought Martindale Melvin"]}, {"id": "terroristactivity12", "Geos": ["Goldtron", "Singapore", "S$8.85", "S$2.10"], "People": ["Berger International", "Eyre Martindale", "Hannigan Wickham", "Vastopolis", "Fu Yu Manufacturing"]}, {"id": "terroristactivity13", "Geos": ["Thailand", "Bangkok"], "People": ["Baier Rousseau", "Chat Thai", "Puleo Leak", "Bevis", "Rhymes Hugh", "Sampson Hoffmann", "Jack", "Carrell", "Bevis Silpa-Sadler", "Rhymes", "Jack Lou", "Carrell Ko", "Vastopolis", "Dharma"]}, {"id": "terroristactivity14", "Geos": ["Argentina", "U.S."], "People": ["Selective Buying"]}, {"id": "terroristactivity15", "Geos": ["Boise", "Idaho"], "People": ["Fastest Pace"]}, {"id": "terroristactivity16", "Geos": [], "People": ["Gatlin", "Games", "Keating Will Cheer", "Gay Allena Jr.", "Vastopolis", "Charlette Gatlin", "Gaye Allena Jr."]}, {"id": "terroristactivity17", "Geos": ["U.S.", "California"], "People": ["Westside", "J. Fredrick Sweeney", "Stefan Jami Plank", "Jami P. Isreal", "Sue Auto Maker"]}, {"id": "terroristactivity18", "Geos": ["U.S."], "People": ["Xander Mellish", "Davina Jeana"]}, {"id": "terroristactivity19", "Geos": [], "People": []}, {"id": "terroristactivity20", "Geos": ["Iraq", "Toronto", "U.S."], "People": ["Klingensmith", "Nygaard Klingensmith"]}, {"id": "terroristactivity21", "Geos": [], "People": ["Vastopolis"]}, {"id": "terroristactivity22", "Geos": ["Markita Beach", "Argentina", "Calif.", "U.S.", "Boyce Deluna", "Vietnam", "Poland"], "People": ["Jone Walz", "Beach", "Rode", "Roberto Mize", "Crabb", "Walz"]}, {"id": "terroristactivity23", "Geos": ["Toulouse", "Britain", "Hamburg", "Spain", "London", "U.S.", "France", "Germany", "LONDON", "Casa"], "People": ["Aerospatiale SA", "Sanjuana Mose", "Restructurings Ahead Aerospatiale", "Chrissy Avis", "Nicolas"]}, {"id": "terroristactivity24", "Geos": ["Osaka", "U.S.", "London"], "People": ["Davina Kirby", "Bower Wyman", "Copper", "Kirby", "Five Percent", "Wyman", "Vastopolis"]}, {"id": "terroristactivity26", "Geos": ["Cincinnati"], "People": ["Julee Kao"]}, {"id": "terroristactivity27", "Geos": ["San Diego", "Kansan", "California"], "People": ["Bay Buchanan", "Dodd", "Stevie Guthrie", "Mikki Luong", "Christa Childers", "Roni Reatha", "Booth", "Pat Buchanan", "Jackelyn Booth's", "Derryberry", "Vastopolis", "Petra Winford", "Rufina Ramires", "Reanna", "Codi"]}, {"id": "terroristactivity28", "Geos": ["Milan", "Wilkey", "Italy"], "People": ["Stultz", "Marcus Hudak", "Francisca Simmon", "Carlo De Benedetti", "Sutphin", "Francesconi", "Simmon", "Assogestioni", "Albrecht Hostetler", "Suspended Sutphin", "Walker Boyce", "Packer"]}, {"id": "terroristactivity29", "Geos": ["Lalonde", "San Francisco", "London", "U.S.", "Uptown", "Germany", "Suburbia", "Nice"], "People": ["Lindsay", "Morningstar", "Michaele Bennie", "Jackelyn Bambi", "Martina Skaggs", "Ericka Dailey", "Mitsuko Barnette", "Anette Dick", "R. Cary", "Petra Yu", "Dick", "Vastopolis", "Kendra Gretchen", "Roberto Lindsay"]}, {"id": "terroristactivity30", "Geos": ["Texas", "Plano"], "People": []}, {"id": "terroristactivity31", "Geos": ["Dayton", "Ohio"], "People": ["Suburbia"]}, {"id": "terroristactivity32", "Geos": ["Norwalk", "Conn."], "People": ["Lapierre"]}, {"id": "terroristactivity33", "Geos": ["Santa Clara", "Calif.", "Results"], "People": ["Vastopolis"]}, {"id": "terroristactivity34", "Geos": [], "People": ["Nutricia"]}, {"id": "terroristactivity35", "Geos": ["Cincinnati"], "People": ["Suazo", "Michaele Suazo", "Vastopolis", "Elane Mcglynn", "Mcglynn", "Thomasina Neil", "Xylan", "Indexes Drop", "Vastsoft Continues"]}, {"id": "terroristactivity36", "Geos": ["N.J.", "U.S.", "Uptown", "New Jersey"], "People": ["Capoten", "Taxol", "Morris Plains", "Islas Baggett", "Baggett"]}, {"id": "terroristactivity37", "Geos": ["Japan", "Tokyo", "U.S."], "People": ["Cliff", "Kessel Kurtz", "Sallee Iles", "Harlan Solano", "Roseberry Trusty", "Vastopolis", "Solano"]}, {"id": "terroristactivity38", "Geos": ["Indonesia"], "People": ["Parks Lira", "Vastopolis"]}, {"id": "terroristactivity39", "Geos": ["Dye"], "People": ["Allene Gale", "Patrick Ewing", "Markita Elson", "Alonzo Mourning", "Hubert", "Christa Galvan", "Lasandra Lindsay", "Russell Caulfield", "Bayne Rowley", "Caulfield", "O'Neil", "Cap Changes", "Carlo Hubert", "Allena Hoyt", "Reid Wilton", "Lakers", "Lyle ``Magic'' Jona", "Bradley Bruner", "Dora Ramsey", "Gaye Crockett", "Schmit", "Markita Conn.", "Michaele Josefa", "Rickey O'Neil", "Jesica Simonne"]}, {"id": "terroristactivity40", "Geos": [], "People": ["Crouch", "Roberta Goins", "Rexene", "Ricki P. Barr", "Jone M. Hagerty", "Vastopolis"]}, {"id": "terroristactivity41", "Geos": ["Japan", "U.S.", "Uptown"], "People": ["Martina Standard", "Vastopolis", "W. Whitney Walston"]}, {"id": "terroristactivity42", "Geos": ["N.C.", "HILL"], "People": ["Wills", "Adela Wills", "Kane Santo", "Nathanial Gullett"]}, {"id": "terroristactivity43", "Geos": ["Baltimore", "Va", "U.S.", "Richmond"], "People": ["Epstein Berry", "Benjamin", "Eugenie Barajas", "Vastopolis", "Davina Benjamin", "Logan", "Suburbia", "Roberto E. Berry"]}, {"id": "terroristactivity44", "Geos": ["Riverside"], "People": ["AH-64A Apaches"]}, {"id": "terroristactivity45", "Geos": ["New Line Cinema", "New Line", "Metro", "U.S.", "Uptown", "Hollywood"], "People": ["Roberto Nagy", "Jimmy Scheffler", "Michaele Lynsey", "Arvilla Paxton", "Kory Barefoot", "Jackelyn Frazier"]}, {"id": "terroristactivity46", "Geos": ["Sweden", "Germany", "U.S.", "Canada"], "People": ["Vastopolis", "Alert On Dental Amalgam"]}, {"id": "terroristactivity47", "Geos": [], "People": ["Vastopolis", "Vastopolis Assessor Refuses", "Daniele Barker"]}, {"id": "terroristactivity48", "Geos": ["Oklahoma", "San Diego"], "People": ["Bruno", "Brumbaugh", "Lasandra Friel", "Susann Esser", "Danae Mcclelland", "Tommie Bretz", "Carlee Rabinowitz", "J.C. Hale's", "Nelson Sol", "Bobby Derryberry", "Solange", "Derryberry", "goodby", "Melvina Bruno", "Bretz", "Khadijah Campbell", "Johnetta Miner"]}, {"id": "terroristactivity49", "Geos": ["West Virginia"], "People": ["Vastopolis", "Morgan"]}, {"id": "terroristactivity51", "Geos": ["Calif.", "U.S."], "People": ["Vastopolis Airport", "Billye Virgil", "Kenyatta Ackerman"]}, {"id": "terroristactivity52", "Geos": ["Washington", "US"], "People": ["Eggleston", "Bruno Eggleston - a"]}, {"id": "terroristactivity53", "Geos": ["Smogtown", "the Ciminally Insane"], "People": []}, {"id": "terroristactivity54", "Geos": ["Us", "Jacques Chafin", "Wyo.", "Wyoming", "Seattle"], "People": ["Webber", "Roebuck", "Cannon Geis", "Shh", "Donetta Aundrea", "Petrina Bilyeu", "Codi", "Bilyeu", "Williemae Roebuck"]}, {"id": "terroristactivity55", "Geos": ["Calif", "Barcelona", "U.S.", "Sweden", "Atlanta"], "People": ["Vastopolis", "Roy", "Raquel Roy", "Johnetta Seaton", "Seaton"]}, {"id": "terroristactivity56", "Geos": ["Frankfurt", "U.S."], "People": ["Vastopolis", "Stocks Slip"]}, {"id": "terroristactivity57", "Geos": ["Wentworth", "Crawley", "San Francisco"], "People": ["Codi", "Vern", "Crawley"]}, {"id": "terroristactivity58", "Geos": ["Argentina"], "People": []}, {"id": "terroristactivity59", "Geos": [], "People": ["Garibay Waltz", "Teasley Atwater", "Brooks Rupe", "Omalley Darby's"]}, {"id": "terroristactivity60", "Geos": ["Hong Kong", "Hong Kong's", "Washington", "China", "the United States", "Beijing"], "People": ["Martine", "Fransisca Martine"]}, {"id": "terroristactivity61", "Geos": ["Bosnia", "Yugoslavia", "Sarajevo", "Netherlands", "BELGRADE", "Belgrade", "The Hague", "U.S."], "People": ["Garvey Shubert", "Garvey Slay", "Henke Packer", "Shubert", "Doster", "Karadzic Resigns From Party", "Packer", "Ricki Doster"]}, {"id": "terroristactivity62", "Geos": ["Taiwan", "China"], "People": ["Herma Mcconnell", "Leeanna Teng-Huong's"]}, {"id": "terroristactivity63", "Geos": [], "People": ["Ebert", "Gregory Ebert"]}, {"id": "terroristactivity64", "Geos": ["New Jersey", "Brazil", "Australia", "Canada", "London", "New York"], "People": ["Corn Belt", "Bernie Rosas"]}, {"id": "terroristactivity65", "Geos": ["Venezuela", "Chimbote", "Lima", "Mexico", "Hallmark", "Peru"], "People": ["Tequila", "Alberta Robinson's", "Miki Noble", "Luise Knighton", "Aldo Gusman", "Hallmark", "Shinn Porterfield Curtis", "Chino"]}, {"id": "terroristactivity66", "Geos": ["Singapore"], "People": []}, {"id": "terroristactivity67", "Geos": ["ValuJet", "WASHINGTON", "Florida", "Vastopolis", "Atlanta"], "People": ["Gregory Ebert", "Lezlie Josefa", "Roberto Paulino", "Ebert"]}, {"id": "terroristactivity68", "Geos": [], "People": ["Samuel Stansbury"]}, {"id": "terroristactivity69", "Geos": ["New York's", "U.S.", "Equitas", "the United States", "New York", "LONDON"], "People": ["Restructuring Plan", "Davina Null", "Edyth J. Kunkle"]}, {"id": "terroristactivity70", "Geos": ["Columbia", "Barton Jessenia"], "People": ["Lisandra Booker", "Janett Yasmin", "Booker", "Roberto Hayward", "Cassie", "Marcelino Cassie", "Jimmy Booker", "Vastopolis", "Roberto Cox"]}, {"id": "terroristactivity71", "Geos": ["Taiwan", "Taipei", "Beijing"], "People": ["Rice", "Jeffery", "Jacobo", "Micropal", "Jahnke Jensen's", "Jardine Fleming", "Patsy Jeffery", "Jardine Fleming Taipei Trust", "Barbara Shaw"]}, {"id": "terroristactivity72", "Geos": ["Orange County", "Calif."], "People": ["Jacob", "Roberto Jacob"]}, {"id": "terroristactivity73", "Geos": ["Sacramento", "San Francisco", "Montana", "Calif.", "U.S.", "SACRAMENTO"], "People": ["Irizarry", "Porter", "Disc", "Silvers", "Theron Silver", "Charlette Porter", "Silver", "Seals"]}, {"id": "terroristactivity74", "Geos": ["Minnesota", "Milwaukee"], "People": ["Rice", "Douglass Davis", "Davida Porter's", "Paulene Konrad's", "Mattie Gayle's", "Kelsey", "Phillip Mack", "Gregorio Hamilton", "Johnetta Rice's", "Davida Morelli's", "Richelle Hodges", "Ciara Bufford", "Tommie Kelsey", "Davida Porter", "Bradley Petree"]}, {"id": "terroristactivity76", "Geos": ["Sydney"], "People": []}, {"id": "terroristactivity77", "Geos": [], "People": ["Marley"]}, {"id": "terroristactivity78", "Geos": ["Indiana", "Oklahoma City", "Arizona", "Dharan", "Valenzuela", "WASHINGTON", "Nunn", "Georgia", "U.S.", "Saudi Arabia"], "People": ["Doak", "Brianna Peter", "Guillory", "Williemae J. Petra", "Jami Obryan", "Dow", "Samantha Lemon", "Ricki Dow", "Lugar", "Jamila S. Doak", "Obryan"]}, {"id": "terroristactivity79", "Geos": [], "People": []}, {"id": "terroristactivity80", "Geos": ["Peoria", "Sacramento", "Ohio", "Ill.", "Iowa", "Circleville", "Red Oak", "Edna", "Minn.", "Calif.", "California", "Moline", "Texas", "Woodland", "WOODLAND"], "People": ["Tess Boris", "Macias", "Magnum 7250", "Vastopolis", "Jennine Deana", "Kent Lynch", "Silvana", "Ezekiel Thorson", "Mckim Macias", "Rutha Arlyne", "Boris", "Magnum", "International Harvester", "Prince", "Bryan Briggs", "Johnetta Arriaga", "Gould", "Roberto Prince", "Raye Yen", "Thorson", "Case", "Rutha", "Davina Dozier", "Woodland", "Jone Silvana"]}, {"id": "terroristactivity81", "Geos": ["Connecticut", "l995", "Conn."], "People": ["Antoinette Sartain", "Sartain", "Chew", "Jena Chew", "Pugh", "Jeremy L. Pugh"]}, {"id": "terroristactivity82", "Geos": ["N.J.", "Penn State"], "People": ["Cyndi Estabrook", "Ellinger", "Cyndy Ellinger", "Enis Rushes"]}, {"id": "terroristactivity83", "Geos": ["Beirut", "U.S."], "People": []}, {"id": "terroristactivity84", "Geos": ["WASHINGTON", "San Francisco", "U.S.", "Magellan", "Nice"], "People": ["Charlette Morrissey", "Bernita Hillman", "Morningstar", "Stauffer", "Roberto Yuan", "Vastopolis", "Roberto J. Barto", "Glenna Lapierre", "Barton Childs", "Make Strong Comeback", "Patience Whitmire", "Barto", "Roberto Roeder", "Schwab", "Childs"]}, {"id": "terroristactivity85", "Geos": ["Luxembourg", "Britain", "London", "the Cayman Islands", "England", "U.S.", "France", "U.K."], "People": ["Dalene Ricki's", "Limon So", "Ricki Sean", "BCCI"]}, {"id": "terroristactivity86", "Geos": ["REDMOND", "Wash.", "Calif."], "People": ["Vastsoft", "Bradley Herold"]}, {"id": "terroristactivity87", "Geos": [], "People": ["International de Reaseguros"]}, {"id": "terroristactivity88", "Geos": ["Bangladesh"], "People": ["French Pillow", "Darby", "Macedo", "Kozlowski", "Maj", "Rahman", "Cols", "Khaleda Zia", "Kill Bangladesh's", "Mansfield", "Box Kozlowski"]}, {"id": "terroristactivity89", "Geos": ["Tokyo", "U.S."], "People": ["Fike Burbank", "Fike Tomes", "Halsey Chamness", "Sorenson", "Saenz", "Step Saudis", "Pyle Palmore", "Alternative Approaches Nevertheless", "Fahd", "Seward Bishop", "Quincy Waltz", "Klatt Al", "Bishop"]}, {"id": "terroristactivity90", "Geos": ["JAPAN", "Japan", "Kawasaki City", "Tokyo", "U.S."], "People": ["Tiger Vacuum Bottle", "Berniece Mcdonnell", "Leeanna Malcolm", "Bricker Storer", "--MASAYOSHI KANABAYASHI", "Wheatley Sandusky"]}, {"id": "terroristactivity91", "Geos": [], "People": ["R.J. Reynolds"]}, {"id": "terroristactivity92", "Geos": ["U.S.", "Va.", "RICHMOND"], "People": ["Rimmer", "Branda Catron", "Roni Rimmer", "Roberta Pierce", "Berry"]}, {"id": "terroristactivity93", "Geos": ["Oklahoma City", "N.Y.", "Paris", "Washington", "U.S."], "People": ["Mikki Peavey", "John F. Kennedy International Airport", "Roberto Francisco"]}, {"id": "terroristactivity94", "Geos": ["Boston"], "People": ["Michael Price", "Jimmy Wittman", "Burwell", "Wittman", "Sean Gaddis", "Jackelyn Burwell", "Gaddis"]}, {"id": "terroristactivity95", "Geos": ["Japan", "U.S.", "Billy Codi"], "People": ["Dana", "Danae Embrey", "Strickland Gales", "Cristopher Kelsey", "Tavarez", "Vastopolis", "Georgeanna Vern", "Danae Tavarez", "Jina Caryl", "Roberto Derryberry", "Comedy Central", "Webber", "Wan Krauss", "Paris", "Mayne", "Gerald Ford", "Albert Webber", "Vern", "Bambi Dean"]}, {"id": "terroristactivity96", "Geos": ["the United States", "U.S.", "NEW YORK"], "People": ["Denny R. Ong"]}, {"id": "terroristactivity97", "Geos": ["Taiwan", "China", "NT$57.50"], "People": ["Leeann", "Leeanna", "Vastopolis", "Enterprises"]}, {"id": "terroristactivity98", "Geos": ["Smogtown"], "People": ["Philip Stanley"]}, {"id": "terroristactivity99", "Geos": ["anesthesia", "New Jersey"], "People": ["Bowles", "Paulene Harrison", "Harrison", "Ricki Aikens", "Joelle Turney", "Kathline Mercado", "F. Michaele Elmer", "Patrina Lockhart", "Penn", "Jami Clemens", "Ray d'Amours", "Vastopolis", "Gay Reynolds", "Marcum", "C. Williemae Morrissey", "Davina Espinoza"]}, {"id": "terroristactivity101", "Geos": ["Papua New Guinea", "Australia", "Bougainville", "Papua New Guinea's"], "People": ["Goliath", "David", "Chanda"]}, {"id": "terroristactivity102", "Geos": ["WASHINGTON", "Chicago"], "People": ["Gay Lyles", "Roberto Derryberry", "Alberta Halina"]}, {"id": "terroristactivity103", "Geos": ["Philippines", "Manila", "Valenzuela", "Pakistan", "Tokyo", "U.S.", "NEW YORK", "New York", "Atlanta"], "People": ["Burney", "Casio", "Maryalice Joana Harrison", "Baggett", "Aldo Baggett", "Eldred", "Echols", "Davina Burney"]}, {"id": "terroristactivity104", "Geos": ["Fla", "Gaylord", "Fort Lauderdale", "New York City's", "New York", "Tenn.", "Nashville"], "People": ["Harriett Dunham", "Dunham", "Vastopolis", "Collins", "Gene", "Ricki H. Collins", "H. Wendell Mccollum", "Wes", "E.W. Wes", "Evans Resigns To Join Huizenga Sports", "Mccollum"]}, {"id": "terroristactivity105", "Geos": ["Hong Kong", "U.S.", "Thailand", "Bangkok"], "People": ["SBC Warburg", "Rozanne Reynaldo", "Kepco", "Dominique Hopp"]}, {"id": "terroristactivity106", "Geos": ["Kyrgyzstan", "Tajikistan", "Pakistan", "Afghanistan", "China", "Uzbekistan", "Kazakstan", "India"], "People": ["Akayev Plans To Continue", "Billy Clayton", "Soukup", "Billie Clay", "Chumley Soukup", "Uzbekistan"]}, {"id": "terroristactivity107", "Geos": ["Telebras", "New York", "The Rio de Janeiro Stock Exchange", "Cemig"], "People": ["Telebras", "Vale"]}, {"id": "terroristactivity108", "Geos": ["Hong Kong", "HK$78.50", "HK$12.90"], "People": ["Vastopolis", "HK$47.40", "Farr Scarlett", "Wynne Hudgens"]}, {"id": "terroristactivity109", "Geos": ["South Korea", "Seoul", "SEOUL"], "People": ["Vastopolis"]}, {"id": "terroristactivity110", "Geos": ["WASHINGTON", "Atlantic City", "Las Vegas", "Ill."], "People": ["Paulene Solange"]}, {"id": "terroristactivity111", "Geos": ["Md.", "Va.", "Frederick", "Brooklyn", "New Jersey", "Blacksburg", "St. Louis", "Alexandria", "Va", "New York", "Idaho"], "People": ["Warren", "Madison", "Welty", "Roberto Melvin", "Wolter", "Kraemer", "Wayne", "Adler Wolter", "Billy Welty", "Roni J. Major", "Elizebeth Wayne", "Iris Kraemer"]}, {"id": "terroristactivity112", "Geos": ["night city", "Hussite"], "People": ["Saavedra", "Martin Delbert Toomey", "Carlota", "Walker Packer", "Tula Litton", "Tooley", "Macedonian ``", "Litton", "Harold Kolb", "Rocha", "Hettie Pinkston", "Mcneal Whiteside", "Crumpton", "Striaz", "Theater Shields"]}, {"id": "terroristactivity113", "Geos": ["N.J.", "Fairfield", "NEW YORK"], "People": []}, {"id": "terroristactivity114", "Geos": ["Mich.", "Colo.", "Englewood", "Merge", "ROC"], "People": ["Johnetta Coates", "Gay Bush", "C.G. Gant"]}, {"id": "terroristactivity115", "Geos": [], "People": []}, {"id": "terroristactivity116", "Geos": ["Houston", "Greenwich", "Missouri", "Arlington", "Dallas", "Conn.", "Texas"], "People": ["Jami O'Remy", "Austin", "Software Etc", "Vastopolis", "O'Remy"]}, {"id": "terroristactivity117", "Geos": ["Frankfurt", "U.S."], "People": ["Bias", "Katheryn Peter", "Scott Sana", "Charlette Mose", "Scottie Sanda", "Huey Schaefer's", "Paulene Mckenna", "Martine Teeters", "Peter", "Huey Schaefer", "Mose", "Pfizer", "Proffitt", "Josephine Blank", "Favorite Things She", "Leonel Schaefer", "Lemay"]}, {"id": "terroristactivity118", "Geos": ["Pa.", "Hartford", "Conn.-based insurer"], "People": []}, {"id": "terroristactivity119", "Geos": ["ATLANTA", "Athletes", "Marta", "Atlanta"], "People": ["Louise Hallmark", "Dillon Pifer", "Pound", "Micheline Garland"]}, {"id": "terroristactivity120", "Geos": ["Indianapolis", "N.J.", "U.S.", "Paxil", "Prozac"], "People": ["Charlette E. Grace", "Islas Baggett", "Johnson", "Prozac"]}, {"id": "terroristactivity121", "Geos": ["Frankfurt"], "People": []}, {"id": "terroristactivity122", "Geos": ["Athens"], "People": ["Francisco", "Jami Obryan", "Roberto Francisco"]}, {"id": "terroristactivity123", "Geos": [], "People": []}, {"id": "terroristactivity124", "Geos": ["Japan", "Taiwan", "NT$523.6"], "People": ["Beach", "Stanley Marine", "Acer", "Disc", "Vastopolis", "Marine"]}, {"id": "terroristactivity126", "Geos": ["Vietnam"], "People": ["Jona", "Georgeanna Shirley", "Osborn", "Roni Reatha's", "Vastopolis", "Trujillo"]}, {"id": "terroristactivity127", "Geos": ["Philadelphia", "San Francisco"], "People": ["Werner Chamberlain Jr.", "Steven Helms", "Bohannon", "Gregorio Heckman", "Perri Brown'", "Marketta Stephens", "Micki Orton", "Jimmie Bohannon", "Ledford", "Chamberlain", "Rico Ledford", "Dusty Baker", "Matthew Bashaw", "Rico Copper", "Magee", "Miki Ahumada"]}, {"id": "terroristactivity128", "Geos": [], "People": ["Vastopolis", "Douglas Lark"]}, {"id": "terroristactivity129", "Geos": ["Dayton", "Mich.", "U.S.", "Lordstown", "Ohio", "Troy"], "People": ["Lear", "Miles", "Donna Parolini", "Olsen", "Ossie Sokol"]}, {"id": "terroristactivity130", "Geos": ["Philadelphia", "Cincinnati"], "People": ["Allen", "Jimmie Vickers", "Johna Allena", "Margene Salcido", "Lenard Colin", "Salcido"]}, {"id": "terroristactivity131", "Geos": ["Iraq", "Light", "U.S."], "People": ["Franco-British", "Valeo"]}, {"id": "terroristactivity132", "Geos": ["America", "Arizona", "Washington", "Hawaii", "WASHINGTON", "Iraq", "Ukraine", "China", "U.S.", "Russia", "the Soviet Union", "North Korea", "Alaska"], "People": ["Johnetta V. Doney", "Bobby Derryberry's", "Roberto Belle", "Josephine Russo", "Jone Buss", "Codi", "Keli Berry", "Reatha", "Fransisca Banda", "Belle", "Derryberry", "Roberto Derryberry's", "Grim Caffey", "Banda", "Buss", "Dole"]}, {"id": "terroristactivity133", "Geos": ["America", "Saudi Arabia''", "Bahrain", "WASHINGTON", "Dhahran", "Qatar", "U.S.", "Kuwait", "Saudi Arabia", "Riyadh"], "People": ["Petra", "Hurd", "Williemae Petra", "Vastopolis", "Peter Will"]}, {"id": "terroristactivity134", "Geos": ["Hong Kong", "HK$78.50", "HK$12.90"], "People": ["Vastopolis", "HK$47.40", "Farr Scarlett", "Wynne Hudgens"]}, {"id": "terroristactivity135", "Geos": ["Telebras", "New York", "The Rio de Janeiro Stock Exchange", "Cemig"], "People": ["Telebras", "Vale"]}, {"id": "terroristactivity136", "Geos": ["Hong Kong", "HK$78.50", "HK$12.90"], "People": ["Vastopolis", "HK$47.40", "Farr Scarlett", "Wynne Hudgens"]}, {"id": "terroristactivity137", "Geos": ["South Korea", "Seoul", "SEOUL"], "People": ["Vastopolis"]}, {"id": "terroristactivity138", "Geos": ["Germany"], "People": ["Spur Market"]}, {"id": "terroristactivity138", "Geos": ["N.Y.", "Houston", "San Diego's", "Tennessee", "Massachusetts", "San Diego", "Okla.", "Georgia", "California", "Hollywood", "Mississippi", "Texas", "Alaska", "Ohio"], "People": ["Fransisca Martinelli", "Copeland", "Strickland Gales", "Moritz", "Martinelli", "Maris Cervantez", "Rosa", "``Bob", "Phillip Sharkey", "Fredda Martinez", "Jackelyn Booth", "Booth", "Kling Gales", "Johnetta Moritz", "Bobby Derryberry", "Derryberry", "Trevor Rosa", "Lance Alexandria", "Colton Lonnie", "Petrina Kirby", "Alexandria", "Petra Winford", "Billy Jan", "Patrina Moran", "Sharkey", "Donella Menefee", "Jan", "Gales", "Kirby", "Lonnie"]}, {"id": "terroristactivity139", "Geos": ["U.K.", "Port Arthur", "Wales", "Tasmania", "Scotland", "Britain", "Australia", "Dunblane", "U.S.", "England"], "People": ["Coles", "Johnetta Hubert", "Alexander Ackerman", "Griffis", "Hubert", "Wolverhampton"]}, {"id": "terroristactivity140", "Geos": ["U.S.", "Descartes"], "People": ["Character Count", "Reatha", "Davina Bruno", "Codi", "Dillon Mcconnell", "Johnetta Paulene Schuster", "Abraham Lindsey", "Francisco Wilkes", "Bobby Derryberry", "Derryberry", "Daniele Nova", "Billy Codi", "Daniele J. Janssen", "Karla F.C. Holloway", "Ricki Niemann", "Georgeanna Simmons", "Danille Centeno", "Mcconnell", "Bowser Derryberry", "Roni Reatha's", "Churchill"]}, {"id": "terroristactivity141", "Geos": ["Mississippi State"], "People": ["Georgeanna", "Guy Killough", "Bryan Wally", "Billy Cannon", "Ericka Peres", "Earle Parker", "Trophy", "Leonarda Noonan", "Heisman Trophy", "Eden Georgeanna", "Georgeann", "Redskins", "Martina", "Charline Ashburn", "Henry Redman", "Jone Overby", "Wendell Martine's", "Celestine", "George Excited"]}, {"id": "terroristactivity142", "Geos": ["Britain", "London", "U.S.", "Equitas", "U.K.", "LONDON", "City"], "People": ["Rimmer", "Benjamin", "Names", "Ronda Rimmer", "Stephine Bumgardner", "Davina Benjamin", "Logan", "Lutine"]}, {"id": "terroristactivity143", "Geos": ["Jubail", "Washington", "Kuwaiti", "Dhahran", "London", "DUBAI", "Afghanistan", "Iran", "U.S.", "Kuwait", "Saudi Arabia", "Riyadh", "United Arab Emirates"], "People": ["Carli", "Fike Meadors", "Williemae Petra", "Reader al-Carli"]}, {"id": "terroristactivity144", "Geos": ["China", "Iraq", "Indonesia"], "People": ["Vastopolis"]}, {"id": "terroristactivity145", "Geos": ["Philippines", "Indonesia", "Thailand", "U.S."], "People": []}, {"id": "terroristactivity146", "Geos": ["Frankfurt", "Germany"], "People": ["Knighton", "--Dagny Cooks", "Jorgenson", "Tindall Knighton", "Derail Plans", "Maastricht", "Blasts Keane", "Grandmother", "Holcomb Jorgenson's"]}, {"id": "terroristactivity147", "Geos": ["Hong Kong", "yuan", "China", "Hong Kong) Ltd.", "U.S.", "Warburg"], "People": ["SBC Warburg", "Vastopolis", "Yue Yuen Industrial Holdings Ltd.", "Jeffery"]}, {"id": "terroristactivity148", "Geos": ["Chalmette", "Ill.", "Glenview", "La.", "U.S.", "Las Vegas"], "People": ["Gregorio Bigler", "Bigler"]}, {"id": "terroristactivity149", "Geos": ["Habsudova", "Calif", "Indianapolis", "Japan", "Netherlands", "Conn.", "South Africa", "Vail", "Russia", "Germany", "Manhattan Beach"], "People": ["Jimmie Windom", "Petra Haskell", "Tomoko Minor", "Alexander Chisolm", "Penn Boyle", "O'Bosch", "Hartung Phelan", "Alexander O'Bosch", "Lindsey Hood", "Easter Mcclung", "Thomasina Krieger", "Vastopolis", "Tomas Martine", "Barlow", "Ricki Dewall", "Karine Glasgow", "Irina Spirlea", "Daniele Goodrum"]}, {"id": "terroristactivity150", "Geos": ["Asheville", "Ala.", "ATLANTA", "Greece", "Georgia", "Mexico City", "Miami", "Nashville", "America", "Hartsfield", "Atlantan", "Tenn.", "Huntsville", "Tokyo", "Birmingham", "Gamesdom", "Athens", "Atlanta", "Aht", "Games city", "New York", "N.C."], "People": ["Williemae B. Hanh", "Adidas", "Heilman Meiners", "Allyson", "Games", "Williemae Prince ``", "Fredrick Allene's", "Billye", "Player", "Hanh", "Barbie", "Porter Porterfield Mccandless", "Meiners", "Eskimos", "Anette Yuette", "Berry", "Gay Allyson", "Petrina Mejias"]}, {"id": "terroristactivity151", "Geos": ["Turkey"], "People": ["Jerry Loudermilk", "Loudermilk"]}, {"id": "terroristactivity25", "Geos": ["Israel", "U.S.", "Venezuela", "Latham"], "People": ["Latham", "Otilia Latham", "Noyes", "Aldo Noyes", "Perdue Ex-Kunkle's", "Superintendent"]}, {"id": "terroristactivity50", "Geos": ["Boatmen", "St. Louis", "Maryland", "Charlotte", "New York", "N.C.", "New Mexico"], "People": ["Anette Cristopher", "Kenyatta D. Lezlie"]}, {"id": "terroristactivity75", "Geos": ["North Carolina", "Ferreira", "Scotland", "Jona", "Guidry", "Huizenga", "Florida", "Mikki", "Cincinnati", "Miami", "the United States", "Tampa Bay"], "People": ["Jon", "Michaele Jona", "Misti Ferreira", "Davina", "Jona", "Jina Jona", "Dolphins", "Whiting Buell", "Paulene Lund", "Shula", "Donella Ferreira", "Grass Jon", "Carlee Lezlie", "Ferreira", "Georgeanna Yuette", "Dad", "Maryalice Annelle"]}, {"id": "terroristactivity100", "Geos": ["Chicago", "Ill.", "Washington", "Hawaii", "Los Angeles", "U.S.", "Decatur"], "People": ["Terresa Winford", "Winford", "Gonzalez", "Michaele D. Andrew", "Michaele Andrew", "Andrew", "Dylan O. Andrew", "Kenya L. Baker", "I. Wellman"]}, {"id": "terroristactivity125", "Geos": ["South Africa's", "N.J.", "Atlantic City", "NEW YORK", "the United States", "Connecticut", "France", "Bahamas"], "People": ["Soledad Taft", "Hayes", "Dickey Hayes", "Diaz", "Dickey Hayes's", "Taft"]}, {"id": "terroristactivity152", "Geos": ["America", "Chicago", "Hugh Duran's", "Philadelphia", "Minneapolis", "Pennsylvania", "New York City", "New York", "Beltran"], "People": ["Casimira", "Lindsey at Gettysburg", "Thomasina Jeffrey", "Kirby Jr", "Martine Lyman", "Hugh H. Duran", "Hassan S. Ty"]}, {"id": "terroristactivity153", "Geos": ["Philadelphia"], "People": ["Pat", "Jefferey Childers", "Jefferson Midkiff", "Joelle Pat"]}, {"id": "terroristactivity154", "Geos": ["Philadelphia"], "People": ["Vastopolis"]}, {"id": "terroristactivity156", "Geos": ["Bosnia-Herzegovina", "Bosnia", "U.S.", "Sarajevo"], "People": ["Healey Slay", "Garvey Shubert", "Schutz Reichert", "Shubert", "Henke Packer", "Dunigan Coley", "Reichert", "Alexandria Till", "Ricki Doster"]}, {"id": "terroristactivity157", "Geos": [], "People": ["Crutchfield Glenn", "Wong", "Synthia Fitzpatrick", "Samara Cyndy", "Billy Pasquale", "Williemae Poulsen"]}, {"id": "terroristactivity158", "Geos": [], "People": []}, {"id": "terroristactivity159", "Geos": ["Washington", "US"], "People": ["Eggleston", "Bruno Eggleston - a"]}]